{
  "template": {
    "parent": "minecraft:block/cube",
    "textures": {
      "north": "charmony:block/RUNESTONE_runestone_side1",
      "east": "charmony:block/RUNESTONE_runestone_side2",
      "south": "charmony:block/RUNESTONE_runestone_side3",
      "west": "charmony:block/RUNESTONE_runestone_side4",
      "up": "charmony:block/RUNESTONE_runestone_end",
      "down": "charmony:block/RUNESTONE_runestone_end",
      "particle": "charmony:block/RUNESTONE_runestone_end"
    }
  },
  "variants": "runestone"
}